LICENCE
README.md
setup.py
gerenciamento_mysql/__init__.py
gerenciamento_mysql/funcoes.py
gerenciamento_mysql.egg-info/PKG-INFO
gerenciamento_mysql.egg-info/SOURCES.txt
gerenciamento_mysql.egg-info/dependency_links.txt
gerenciamento_mysql.egg-info/requires.txt
gerenciamento_mysql.egg-info/top_level.txt