Metadata-Version: 2.1
Name: gerenciamento-mysql
Version: 0.0.1
Summary: Gerenciador de MYSQL
Author: George Júnior
Author-email: ctt.georgejr@gmail.com
License: MIT License
Keywords: gerenciamento mysql
License-File: LICENCE
